.gitignore
MANIFEST.in
README.rst
bootstrap.py
buildout.cfg
setup.py
collective/__init__.py
collective.portlet.nivoslider.egg-info/PKG-INFO
collective.portlet.nivoslider.egg-info/SOURCES.txt
collective.portlet.nivoslider.egg-info/dependency_links.txt
collective.portlet.nivoslider.egg-info/entry_points.txt
collective.portlet.nivoslider.egg-info/namespace_packages.txt
collective.portlet.nivoslider.egg-info/not-zip-safe
collective.portlet.nivoslider.egg-info/requires.txt
collective.portlet.nivoslider.egg-info/top_level.txt
collective/portlet/__init__.py
collective/portlet/nivoslider/__init__.py
collective/portlet/nivoslider/configure.zcml
collective/portlet/nivoslider/portlet.pt
collective/portlet/nivoslider/portlet.py
collective/portlet/nivoslider/rebuild_i18n.sh
collective/portlet/nivoslider/upgrades.py
collective/portlet/nivoslider/upgrades.zcml
collective/portlet/nivoslider/locales/collective.portlet.nivoslider.pot
collective/portlet/nivoslider/locales/en/LC_MESSAGES/collective.portlet.nivoslider.po
collective/portlet/nivoslider/locales/fr/LC_MESSAGES/collective.portlet.nivoslider.po
collective/portlet/nivoslider/profiles/default/cssregistry.xml
collective/portlet/nivoslider/profiles/default/jsregistry.xml
collective/portlet/nivoslider/profiles/default/metadata.xml
collective/portlet/nivoslider/profiles/default/portlets.xml
docs/HISTORY.txt