Metadata-Version: 1.0
Name: collective.portlet.nivoslider
Version: 1.0
Summary: NivoSlider portlet for Plone
Home-page: https://github.com/collective/collective.portlet.nivoslider
Author: JeanMichel FRANCOIS aka toutpt
Author-email: toutpt@gmail.com
License: GPL
Keywords: plone portlet nivoslider
Platform: UNKNOWN
Classifier: Programming Language :: Python
